{"name":"Proceso Autogestion - Agendamiento de servicios","id":"proceso-autogestion---agendamiento-de-servicios;proceso-autogestion---agendamiento-de-servicios","testSteps":[{"number":1,"description":"Dado el usuario final cuando desee crear o agendar una orden de servicio","duration":13175,"startTime":"2023-10-06T09:08:20.896-05:00[America/Bogota]","screenshots":[{"screenshot":"8efb5a94563558bbc8b400ad9ec84b30908fbd972d756bd3027057f5cd20ab22.png","timeStamp":1696601314071}],"result":"SUCCESS","precondition":false,"level":0,"lineNumber":0,"children":[{"number":2,"description":"Jhon abrir pagina","duration":12301,"startTime":"2023-10-06T09:08:21.752-05:00[America/Bogota]","screenshots":[{"screenshot":"8efb5a94563558bbc8b400ad9ec84b30908fbd972d756bd3027057f5cd20ab22.png","timeStamp":1696601314053}],"result":"SUCCESS","precondition":false,"level":1,"lineNumber":0,"children":[{"number":3,"description":"jhon opens the Object abrir pagina","duration":9088,"startTime":"2023-10-06T09:08:21.794-05:00[America/Bogota]","screenshots":[{"screenshot":"41b6640790f6c035e9cc5560e9e758877bd0fe56c85f51801263ee1bb6d45bf0.png","timeStamp":1696601310880}],"result":"SUCCESS","precondition":false,"level":2,"lineNumber":0}]}]},{"number":4,"description":"Cuando Crea la orden de servicio","duration":61185,"startTime":"2023-10-06T09:08:34.072-05:00[America/Bogota]","screenshots":[{"screenshot":"8efb5a94563558bbc8b400ad9ec84b30908fbd972d756bd3027057f5cd20ab22.png","timeStamp":1696601375257}],"result":"SUCCESS","precondition":false,"level":0,"lineNumber":0,"children":[{"number":5,"description":"Jhon autogestion","duration":60857,"startTime":"2023-10-06T09:08:34.379-05:00[America/Bogota]","screenshots":[{"screenshot":"8efb5a94563558bbc8b400ad9ec84b30908fbd972d756bd3027057f5cd20ab22.png","timeStamp":1696601375236}],"result":"SUCCESS","precondition":false,"level":1,"lineNumber":0,"children":[{"number":6,"description":"jhon clicks on Heabeas Data","duration":818,"startTime":"2023-10-06T09:08:44.633-05:00[America/Bogota]","screenshots":[{"screenshot":"7af8208fe915f7a41acecc021514ccc01ebb7aa5a9bd2e380869e1e95c65950a.png","timeStamp":1696601325451}],"result":"SUCCESS","precondition":false,"level":2,"lineNumber":0},{"number":7,"description":"jhon clicks on Seleccionar el tipo de documento","duration":837,"startTime":"2023-10-06T09:08:45.454-05:00[America/Bogota]","screenshots":[{"screenshot":"461c5ee614e8508c45e933139d5b3ceed67746266bf7099abf9b6b6aa4135e41.png","timeStamp":1696601326290}],"result":"SUCCESS","precondition":false,"level":2,"lineNumber":0},{"number":8,"description":"Jhon seleccionar tipo documento","duration":500,"startTime":"2023-10-06T09:08:46.293-05:00[America/Bogota]","screenshots":[{"screenshot":"bd675a25b98b32d96dc9012b1f93b4f64155102df4a617161f46385ff5d4cb14.png","timeStamp":1696601326793}],"result":"SUCCESS","precondition":false,"level":2,"lineNumber":0},{"number":9,"description":"jhon enters \u0027992284749\u0027 into Seleccionar el tipo de documento","duration":1100,"startTime":"2023-10-06T09:08:46.796-05:00[America/Bogota]","screenshots":[{"screenshot":"082e3706d7c9a6815fe14a6685b742b23a199e68f80cdc2e2f34e61ddd4638da.png","timeStamp":1696601327896}],"result":"SUCCESS","precondition":false,"level":2,"lineNumber":0},{"number":10,"description":"jhon enters \u0027jhon.quinones1@infotrack.com.co\u0027 into ¿Cuál es tu correo electrónico?","duration":857,"startTime":"2023-10-06T09:08:47.899-05:00[America/Bogota]","screenshots":[{"screenshot":"b5a7c551d85412d768aa4ac64675726d8e5a7afd44ea4df5832d00ed1bc46463.png","timeStamp":1696601328756}],"result":"SUCCESS","precondition":false,"level":2,"lineNumber":0},{"number":11,"description":"jhon enters \u0027Usuario\u0027 into ¿Cuales son tus apellidos?","duration":654,"startTime":"2023-10-06T09:08:53.969-05:00[America/Bogota]","screenshots":[{"screenshot":"eff62fa094cd3f86d56f5baedd31fc2a66fe5551aacc2974ac902914233a0aee.png","timeStamp":1696601334623}],"result":"SUCCESS","precondition":false,"level":2,"lineNumber":0},{"number":12,"description":"jhon enters \u00271.0\u0027 into ¿Cual es tu telefono fijo?","duration":687,"startTime":"2023-10-06T09:08:54.625-05:00[America/Bogota]","screenshots":[{"screenshot":"4ecef4d6bc48efcdb1fc7d2889fdebe221e92ee46543999aa0409e6ec0cbd8a5.png","timeStamp":1696601335312}],"result":"SUCCESS","precondition":false,"level":2,"lineNumber":0},{"number":13,"description":"jhon enters \u00273.0E9\u0027 into Ingresa tu numero celular","duration":669,"startTime":"2023-10-06T09:08:55.338-05:00[America/Bogota]","screenshots":[{"screenshot":"a2b4eedbddbb937a2bf1326e1e63a56d95cffd4fe7210f09465689b86e564af2.png","timeStamp":1696601336007}],"result":"SUCCESS","precondition":false,"level":2,"lineNumber":0},{"number":14,"description":"jhon enters \u00273.0E9\u0027 into Seleccionar el tipo de documento","duration":671,"startTime":"2023-10-06T09:08:56.009-05:00[America/Bogota]","screenshots":[{"screenshot":"a33234aaa4f1c94356ead0d01ed26ef6a43544585c5fc4712912aa2663f83ed7.png","timeStamp":1696601336680}],"result":"SUCCESS","precondition":false,"level":2,"lineNumber":0},{"number":15,"description":"jhon clicks on Continuar","duration":446,"startTime":"2023-10-06T09:08:56.682-05:00[America/Bogota]","screenshots":[{"screenshot":"ce1dcea94a9a70f5aeb8cd362dc45549678a191690343bfea60dbdb40a8b0f33.png","timeStamp":1696601337128}],"result":"SUCCESS","precondition":false,"level":2,"lineNumber":0},{"number":16,"description":"jhon enters \u0027Bogota\u0027 into Ciudad","duration":679,"startTime":"2023-10-06T09:08:57.412-05:00[America/Bogota]","screenshots":[{"screenshot":"834dcc014db6d7398d1aa91487b79f3c80e088a2413a0b7ab2ca625459092b60.png","timeStamp":1696601338091}],"result":"SUCCESS","precondition":false,"level":2,"lineNumber":0},{"number":17,"description":"jhon clicks on Lista de ciudades","duration":390,"startTime":"2023-10-06T09:08:58.093-05:00[America/Bogota]","screenshots":[{"screenshot":"5684542ec712166fd9c7de83827313d121554964e57052e02bb7e564f0321abd.png","timeStamp":1696601338483}],"result":"SUCCESS","precondition":false,"level":2,"lineNumber":0},{"number":18,"description":"jhon enters \u0027Av. C. 127\u0027 into Direccion","duration":704,"startTime":"2023-10-06T09:08:58.485-05:00[America/Bogota]","screenshots":[{"screenshot":"7146a540f3a2019fdda8823d3aa96d10d0d24366e93e6185a74cb1c63f498449.png","timeStamp":1696601339188}],"result":"SUCCESS","precondition":false,"level":2,"lineNumber":0},{"number":19,"description":"jhon clicks on Buscar la dirección","duration":454,"startTime":"2023-10-06T09:08:59.190-05:00[America/Bogota]","screenshots":[{"screenshot":"520782b3454795a0812cef12214d14012b1922dce8936c3ddcf402c80937e1d3.png","timeStamp":1696601339644}],"result":"SUCCESS","precondition":false,"level":2,"lineNumber":0},{"number":20,"description":"jhon enters \u0027Norte\u0027 into Datos adicionales","duration":704,"startTime":"2023-10-06T09:09:05.657-05:00[America/Bogota]","screenshots":[{"screenshot":"d308e81ebe9303a1515ba8400cbbe0d1772d478b87fc665a6b608d81d1d9e8c0.png","timeStamp":1696601346361}],"result":"SUCCESS","precondition":false,"level":2,"lineNumber":0},{"number":21,"description":"jhon clicks on Continuar ubicación servicio","duration":470,"startTime":"2023-10-06T09:09:06.518-05:00[America/Bogota]","screenshots":[{"screenshot":"c811eb0672d3173fc2e791ea029f9fe7617d577c7212486dbd7a919c8c1680f6.png","timeStamp":1696601346988}],"result":"SUCCESS","precondition":false,"level":2,"lineNumber":0},{"number":22,"description":"jhon enters \u0027Garantia\u0027 into ¿Qué tipo de servicio solicitas?","duration":867,"startTime":"2023-10-06T09:09:07.603-05:00[America/Bogota]","screenshots":[{"screenshot":"48c1773ac407e3abf0d1aff4b9d74f8b3ef97a168e7a413693862bd00061e083.png","timeStamp":1696601348470}],"result":"SUCCESS","precondition":false,"level":2,"lineNumber":0},{"number":23,"description":"jhon clicks on ¿Qué tipo de servicio solicitas? Lista","duration":433,"startTime":"2023-10-06T09:09:08.472-05:00[America/Bogota]","screenshots":[{"screenshot":"421c13036a8f37fd269a52850296a441ddc257fd6105b8a412efe8cc76e21d21.png","timeStamp":1696601348905}],"result":"SUCCESS","precondition":false,"level":2,"lineNumber":0},{"number":24,"description":"jhon enters \u0027NEVERA 5.3 PIES ALMENDRA\u0027 into ¿Cuál es el producto?","duration":781,"startTime":"2023-10-06T09:09:08.907-05:00[America/Bogota]","screenshots":[{"screenshot":"1c8a4d966a010aff15a5d23a7c0552b1c2ea876ed64ea7e154a9d201a51df00b.png","timeStamp":1696601349688}],"result":"SUCCESS","precondition":false,"level":2,"lineNumber":0},{"number":25,"description":"jhon clicks on ¿Cuál es el producto? Lista","duration":399,"startTime":"2023-10-06T09:09:09.692-05:00[America/Bogota]","screenshots":[{"screenshot":"2bd4c206ac0c82067a42dec123f9b261ec9bb6e0dbd8c074465692e67ce159ae.png","timeStamp":1696601350091}],"result":"SUCCESS","precondition":false,"level":2,"lineNumber":0},{"number":26,"description":"jhon enters \u0027BOTA AGUA\u0027 into ¿Cuál es el motivo de la reparación?","duration":620,"startTime":"2023-10-06T09:09:10.093-05:00[America/Bogota]","screenshots":[{"screenshot":"13fc466f51e9b47778718800c2d68dcd83453dcfda40c71da631bbd3e578cc9f.png","timeStamp":1696601350713}],"result":"SUCCESS","precondition":false,"level":2,"lineNumber":0},{"number":27,"description":"jhon clicks on ¿Cuál es el motivo de la reparación? Lista","duration":342,"startTime":"2023-10-06T09:09:10.714-05:00[America/Bogota]","screenshots":[{"screenshot":"cd3f8687ba7fdf547ec4eb599ebac3c2d2e5f5ed21430c598d9d7641cd254682.png","timeStamp":1696601351056}],"result":"SUCCESS","precondition":false,"level":2,"lineNumber":0},{"number":28,"description":"jhon enters \u0027QA AUTOMOTION1\u0027 into observaciones","duration":747,"startTime":"2023-10-06T09:09:11.058-05:00[America/Bogota]","screenshots":[{"screenshot":"2e6cb1bffb09b4b948f7e3ba2c8ca6c53f70d4c3735afa20d56ccf33687d837f.png","timeStamp":1696601351805}],"result":"SUCCESS","precondition":false,"level":2,"lineNumber":0},{"number":29,"description":"jhon clicks on Rango AM","duration":502,"startTime":"2023-10-06T09:09:17.821-05:00[America/Bogota]","screenshots":[{"screenshot":"b17ec1511dc755b63a470cfd46565819177d13edf456500cbc7a9f1d776884f8.png","timeStamp":1696601358323}],"result":"SUCCESS","precondition":false,"level":2,"lineNumber":0},{"number":30,"description":"jhon enters \u0027992284749\u0027 into Rango PM","duration":649,"startTime":"2023-10-06T09:09:25.018-05:00[America/Bogota]","screenshots":[{"screenshot":"24e6f83bb3b6064f7d601d5ae3b61442d5ffc307fdecb0d658cb02fe0da9e102.png","timeStamp":1696601365667}],"result":"SUCCESS","precondition":false,"level":2,"lineNumber":0},{"number":31,"description":"jhon clicks on Fecha","duration":544,"startTime":"2023-10-06T09:09:25.841-05:00[America/Bogota]","screenshots":[{"screenshot":"25905b6b772596d6966be06e3f8b5f8ad9b2ba9a7eb8d55017cae6c662fd0f12.png","timeStamp":1696601366384}],"result":"SUCCESS","precondition":false,"level":2,"lineNumber":0},{"number":32,"description":"jhon clicks on Confirmar Fecha seleccionada","duration":512,"startTime":"2023-10-06T09:09:26.386-05:00[America/Bogota]","screenshots":[{"screenshot":"08edbcef5b23e4b58b45b8dfb56ea3600d34f18f0af15dc0afd4d46cadf18f84.png","timeStamp":1696601366898}],"result":"SUCCESS","precondition":false,"level":2,"lineNumber":0},{"number":33,"description":"jhon clicks on Programar","duration":437,"startTime":"2023-10-06T09:09:26.900-05:00[America/Bogota]","screenshots":[{"screenshot":"1418c41e8430d62471b4bd2e65bf3c093a8f9c886590dc020abba906567ca145.png","timeStamp":1696601367337}],"result":"SUCCESS","precondition":false,"level":2,"lineNumber":0},{"number":34,"description":"Then ver orden servicio should be a value equal to \u0027Tu servicio ha sido programado\u0027","duration":235,"startTime":"2023-10-06T09:09:27.998-05:00[America/Bogota]","screenshots":[{"screenshot":"e049adb60872c8de818fc8f5eefbd27433185b1af68bf4409e63ec758e71e0f9.png","timeStamp":1696601368233}],"result":"SUCCESS","precondition":false,"level":2,"lineNumber":0},{"number":35,"description":"jhon clicks on Finalizar Orden de servicio","duration":885,"startTime":"2023-10-06T09:09:31.386-05:00[America/Bogota]","screenshots":[{"screenshot":"43b385713ea71fba9770c910eeeac4f9b2feeeea3aa4413e1c6bb79d9c26916b.png","timeStamp":1696601372271}],"result":"SUCCESS","precondition":false,"level":2,"lineNumber":0}]}]},{"number":36,"description":"Entonces verifica que se creo correctamente la orden de servicio","duration":23,"startTime":"2023-10-06T09:09:35.258-05:00[America/Bogota]","screenshots":[{"screenshot":"8efb5a94563558bbc8b400ad9ec84b30908fbd972d756bd3027057f5cd20ab22.png","timeStamp":1696601375281}],"result":"SUCCESS","precondition":false,"level":0,"lineNumber":0}],"userStory":{"id":"proceso-autogestion---agendamiento-de-servicios","storyName":"Proceso Autogestion - Agendamiento de servicios","path":"src/test/resources/features/Autogestion.feature","type":"feature"},"featureTag":{"name":"Features/Proceso Autogestion - Agendamiento de servicios","type":"feature","displayName":"Features/Proceso Autogestion - Agendamiento de servicios"},"title":"Proceso Autogestion - Agendamiento de servicios","tags":[{"name":"CP001_Creacion_OrdenServicio","type":"tag","displayName":"CP001_Creacion_OrdenServicio"},{"name":"Creacion_OrdenServicio","type":"tag","displayName":"Creacion_OrdenServicio"},{"name":"Proceso Autogestion - Agendamiento de servicios","type":"feature","displayName":"Proceso Autogestion - Agendamiento de servicios"}],"startTime":"2023-10-06T09:08:20.696-05:00[America/Bogota]","duration":74587,"projectKey":"","sessionId":"aa7649246734de0afbc04e9a561aeeeb","driver":"chrome:jhon","isManualTestingUpToDate":false,"manual":false,"testSource":"Cucumber","actors":[{"name":"jhon","can":["browse the web"]}],"result":"SUCCESS"}