{"name":"Proceso Autogestion - Agendamiento de servicios","id":"proceso-autogestion---agendamiento-de-servicios;proceso-autogestion---agendamiento-de-servicios","testSteps":[{"number":1,"description":"Dado el usuario final cuando desee crear o agendar una orden de servicio","duration":15397,"startTime":"2023-08-18T09:11:37.981-05:00[America/Bogota]","screenshots":[{"screenshot":"96456ebb1bf739681a22be618260356f706a0668c31313ad7b958b190ffa0afd.png","timeStamp":1692367913378}],"result":"SUCCESS","precondition":false,"level":0,"lineNumber":0,"children":[{"number":2,"description":"Jhon abrir pagina","duration":14516,"startTime":"2023-08-18T09:11:38.846-05:00[America/Bogota]","screenshots":[{"screenshot":"96456ebb1bf739681a22be618260356f706a0668c31313ad7b958b190ffa0afd.png","timeStamp":1692367913362}],"result":"SUCCESS","precondition":false,"level":1,"lineNumber":0,"children":[{"number":3,"description":"jhon opens the Object abrir pagina","duration":8133,"startTime":"2023-08-18T09:11:38.882-05:00[America/Bogota]","screenshots":[{"screenshot":"1f4be1e83d88c384da7652312fc1994bf2388abc318cc3113ceaa0a63c23d305.png","timeStamp":1692367907013}],"result":"SUCCESS","precondition":false,"level":2,"lineNumber":0}]}]},{"number":4,"description":"Cuando Crea la orden de servicio","duration":76577,"startTime":"2023-08-18T09:11:53.379-05:00[America/Bogota]","screenshots":[{"screenshot":"96456ebb1bf739681a22be618260356f706a0668c31313ad7b958b190ffa0afd.png","timeStamp":1692367989956}],"result":"SUCCESS","precondition":false,"level":0,"lineNumber":0,"children":[{"number":5,"description":"Jhon autogestion","duration":76297,"startTime":"2023-08-18T09:11:53.643-05:00[America/Bogota]","screenshots":[{"screenshot":"96456ebb1bf739681a22be618260356f706a0668c31313ad7b958b190ffa0afd.png","timeStamp":1692367989940}],"result":"SUCCESS","precondition":false,"level":1,"lineNumber":0,"children":[{"number":6,"description":"jhon clicks on Heabeas Data","duration":662,"startTime":"2023-08-18T09:12:03.711-05:00[America/Bogota]","screenshots":[{"screenshot":"37f0dc3fada953f1ad53eacff6bc6c2f6cbcf8592debcf898f44a3e9bb50db38.png","timeStamp":1692367924373}],"result":"SUCCESS","precondition":false,"level":2,"lineNumber":0},{"number":7,"description":"jhon clicks on Seleccionar el tipo de documento","duration":612,"startTime":"2023-08-18T09:12:04.376-05:00[America/Bogota]","screenshots":[{"screenshot":"338e1a58d5e2e96857c248e1fbe3717742f82f918d6e9acbd1a546c4b66f28f8.png","timeStamp":1692367924987}],"result":"SUCCESS","precondition":false,"level":2,"lineNumber":0},{"number":8,"description":"Jhon seleccionar tipo documento","duration":461,"startTime":"2023-08-18T09:12:04.991-05:00[America/Bogota]","screenshots":[{"screenshot":"e5f048f993cae7eaaf750d37f8043b853a1d07ae7533a5c2aeb78b3f6c0e1c10.png","timeStamp":1692367925452}],"result":"SUCCESS","precondition":false,"level":2,"lineNumber":0},{"number":9,"description":"jhon enters \u00271388400881\u0027 into Seleccionar el tipo de documento","duration":914,"startTime":"2023-08-18T09:12:05.456-05:00[America/Bogota]","screenshots":[{"screenshot":"709a30be6bc9bc2d85216d6bfc9bb5dda3858a5119daaacabec8977be1f7f5d9.png","timeStamp":1692367926370}],"result":"SUCCESS","precondition":false,"level":2,"lineNumber":0},{"number":10,"description":"jhon enters \u0027jhon.quinones1@infotrack.com.co\u0027 into ¿Cuál es tu correo electrónico?","duration":1091,"startTime":"2023-08-18T09:12:06.372-05:00[America/Bogota]","screenshots":[{"screenshot":"859375a92d9d7a1cccd9f0ed8642de70e7044eb1d6f199c8bada9f1569e5eb48.png","timeStamp":1692367927463}],"result":"SUCCESS","precondition":false,"level":2,"lineNumber":0},{"number":11,"description":"jhon enters \u0027Usuario\u0027 into ¿Cuales son tus apellidos?","duration":605,"startTime":"2023-08-18T09:12:12.638-05:00[America/Bogota]","screenshots":[{"screenshot":"04335dff28af6fe878cb12bc80a3bbb51c958e7c755a7d9e8ec5dd93f4b2a2fa.png","timeStamp":1692367933243}],"result":"SUCCESS","precondition":false,"level":2,"lineNumber":0},{"number":12,"description":"jhon enters \u00271.0\u0027 into ¿Cual es tu telefono fijo?","duration":578,"startTime":"2023-08-18T09:12:13.245-05:00[America/Bogota]","screenshots":[{"screenshot":"ca8bf7e6d1bdddecc80ea972b183dbc126e3ae0f4b4c334181c9fe897521628d.png","timeStamp":1692367933823}],"result":"SUCCESS","precondition":false,"level":2,"lineNumber":0},{"number":13,"description":"jhon enters \u00273.0E9\u0027 into Ingresa tu numero celular","duration":636,"startTime":"2023-08-18T09:12:13.842-05:00[America/Bogota]","screenshots":[{"screenshot":"e2345d2fc4a8dca335f25f253b7f04207955a9e6a1fcca036a1fe5ae56453cb3.png","timeStamp":1692367934478}],"result":"SUCCESS","precondition":false,"level":2,"lineNumber":0},{"number":14,"description":"jhon enters \u00273.0E9\u0027 into Seleccionar el tipo de documento","duration":604,"startTime":"2023-08-18T09:12:14.480-05:00[America/Bogota]","screenshots":[{"screenshot":"c78c07e36213dd98df0aecf94368db9812ca5c27f1a1cb248bfbbe8b72a4a4ee.png","timeStamp":1692367935084}],"result":"SUCCESS","precondition":false,"level":2,"lineNumber":0},{"number":15,"description":"jhon clicks on Continuar","duration":465,"startTime":"2023-08-18T09:12:15.087-05:00[America/Bogota]","screenshots":[{"screenshot":"a7e7933b98fbe2e3a79c1d0dfad85fe55115c07e887165044ca4c6a8daa0583d.png","timeStamp":1692367935552}],"result":"SUCCESS","precondition":false,"level":2,"lineNumber":0},{"number":16,"description":"jhon enters \u0027Bogota\u0027 into Ciudad","duration":637,"startTime":"2023-08-18T09:12:20.584-05:00[America/Bogota]","screenshots":[{"screenshot":"fc18ed372f59672e4d9beec6456409a0c364e4333f8d07545d2320059d257c2a.png","timeStamp":1692367941221}],"result":"SUCCESS","precondition":false,"level":2,"lineNumber":0},{"number":17,"description":"jhon clicks on Lista de ciudades","duration":375,"startTime":"2023-08-18T09:12:21.223-05:00[America/Bogota]","screenshots":[{"screenshot":"1a7c85d3941a85f0dd1c3aff892ba807f5c7e9d38f8e554ac7e8f293c1918ab1.png","timeStamp":1692367941598}],"result":"SUCCESS","precondition":false,"level":2,"lineNumber":0},{"number":18,"description":"jhon enters \u0027Av. C. 127\u0027 into Direccion","duration":615,"startTime":"2023-08-18T09:12:21.602-05:00[America/Bogota]","screenshots":[{"screenshot":"c0b5db4c6edbd18d5ac74e77f7d63d973ffd67664299501d11a63386754d6c66.png","timeStamp":1692367942217}],"result":"SUCCESS","precondition":false,"level":2,"lineNumber":0},{"number":19,"description":"jhon clicks on Buscar la dirección","duration":478,"startTime":"2023-08-18T09:12:22.219-05:00[America/Bogota]","screenshots":[{"screenshot":"8d4aa6664eea2cfa0cb4a0f7fc67530576f7991b79bed35e5b514528ead3bf0e.png","timeStamp":1692367942697}],"result":"SUCCESS","precondition":false,"level":2,"lineNumber":0},{"number":20,"description":"jhon enters \u0027Norte\u0027 into Datos adicionales","duration":671,"startTime":"2023-08-18T09:12:28.722-05:00[America/Bogota]","screenshots":[{"screenshot":"051b57057ff344e80fc376f0439423889dd6a1869b076f96f909df574607906a.png","timeStamp":1692367949393}],"result":"SUCCESS","precondition":false,"level":2,"lineNumber":0},{"number":21,"description":"jhon clicks on Continuar ubicación servicio","duration":455,"startTime":"2023-08-18T09:12:29.492-05:00[America/Bogota]","screenshots":[{"screenshot":"4a1c8e0284cc0f11a8b9454baa4ba3d66408d1d38b007be3130f815c1f233cce.png","timeStamp":1692367949947}],"result":"SUCCESS","precondition":false,"level":2,"lineNumber":0},{"number":22,"description":"jhon enters \u0027Garantia\u0027 into ¿Qué tipo de servicio solicitas?","duration":692,"startTime":"2023-08-18T09:12:36.013-05:00[America/Bogota]","screenshots":[{"screenshot":"039e9d8c2ecb0dcebf53e94ae27ea4eb929cd635e634ee42aa0e3271894cd4da.png","timeStamp":1692367956705}],"result":"SUCCESS","precondition":false,"level":2,"lineNumber":0},{"number":23,"description":"jhon clicks on ¿Qué tipo de servicio solicitas? Lista","duration":396,"startTime":"2023-08-18T09:12:36.707-05:00[America/Bogota]","screenshots":[{"screenshot":"c584ab157356682b934d7238e1e89948834b6e1cb31c38e38c014e4db7340ddc.png","timeStamp":1692367957103}],"result":"SUCCESS","precondition":false,"level":2,"lineNumber":0},{"number":24,"description":"jhon enters \u0027NEVERA 5.3 PIES ALMENDRA\u0027 into ¿Cuál es el producto?","duration":763,"startTime":"2023-08-18T09:12:37.105-05:00[America/Bogota]","screenshots":[{"screenshot":"1b7167f4072652316f15ca29baff35ab0a498114a13eea09ea4127e2eb48242a.png","timeStamp":1692367957868}],"result":"SUCCESS","precondition":false,"level":2,"lineNumber":0},{"number":25,"description":"jhon clicks on ¿Cuál es el producto? Lista","duration":385,"startTime":"2023-08-18T09:12:37.869-05:00[America/Bogota]","screenshots":[{"screenshot":"e51e8dd6ca626f45a87479d748225dd2350bff14ccaf672f268dd634faa93e60.png","timeStamp":1692367958253}],"result":"SUCCESS","precondition":false,"level":2,"lineNumber":0},{"number":26,"description":"jhon enters \u0027BOTA AGUA\u0027 into ¿Cuál es el motivo de la reparación?","duration":661,"startTime":"2023-08-18T09:12:38.255-05:00[America/Bogota]","screenshots":[{"screenshot":"5da6ea9daf8549e09ff235b9de4df2f86dc2ff55f58ceac80d9e7a57f4fb4a6d.png","timeStamp":1692367958916}],"result":"SUCCESS","precondition":false,"level":2,"lineNumber":0},{"number":27,"description":"jhon clicks on ¿Cuál es el motivo de la reparación? Lista","duration":315,"startTime":"2023-08-18T09:12:38.917-05:00[America/Bogota]","screenshots":[{"screenshot":"117f1bbb525a7710776732d6a28fe6c52b425468fcce84941d3ac0758c32ee7e.png","timeStamp":1692367959232}],"result":"SUCCESS","precondition":false,"level":2,"lineNumber":0},{"number":28,"description":"jhon enters \u0027QA AUTOMOTION1\u0027 into observaciones","duration":688,"startTime":"2023-08-18T09:12:39.233-05:00[America/Bogota]","screenshots":[{"screenshot":"256cc08cc4daa426318bf8a1028955382250ee1a03e36f23983d5fefef716a81.png","timeStamp":1692367959921}],"result":"SUCCESS","precondition":false,"level":2,"lineNumber":0},{"number":29,"description":"jhon clicks on Rango AM","duration":494,"startTime":"2023-08-18T09:12:45.955-05:00[America/Bogota]","screenshots":[{"screenshot":"b6cf9734ed42e78aadc3ce411de6259c741bc96e6f3d10f36e471db6166d820b.png","timeStamp":1692367966449}],"result":"SUCCESS","precondition":false,"level":2,"lineNumber":0},{"number":30,"description":"jhon enters \u00271388400881\u0027 into Rango PM","duration":662,"startTime":"2023-08-18T09:12:53.040-05:00[America/Bogota]","screenshots":[{"screenshot":"18a439acc6d3656ed99cac9b069e34c5c253669fcb678c1c308494cfe225434d.png","timeStamp":1692367973702}],"result":"SUCCESS","precondition":false,"level":2,"lineNumber":0},{"number":31,"description":"jhon clicks on Fecha","duration":494,"startTime":"2023-08-18T09:12:53.704-05:00[America/Bogota]","screenshots":[{"screenshot":"e5613582de0048716d96775cf449ebdffd1974db875b8eeada50cca3859154c9.png","timeStamp":1692367974198}],"result":"SUCCESS","precondition":false,"level":2,"lineNumber":0},{"number":32,"description":"jhon clicks on Confirmar Fecha seleccionada","duration":529,"startTime":"2023-08-18T09:12:54.200-05:00[America/Bogota]","screenshots":[{"screenshot":"ddb0b94bcdc7e3eea36da3cb48ecd689c14b3e1fee19c5fd18ac0dec6a151967.png","timeStamp":1692367974729}],"result":"SUCCESS","precondition":false,"level":2,"lineNumber":0},{"number":33,"description":"jhon clicks on Programar","duration":446,"startTime":"2023-08-18T09:12:54.732-05:00[America/Bogota]","screenshots":[{"screenshot":"84d92d6765b3c68bf61346a4f49ce20b6a608a7253d323254c61aff59e629ead.png","timeStamp":1692367975178}],"result":"SUCCESS","precondition":false,"level":2,"lineNumber":0},{"number":34,"description":"Then ver orden servicio should be a value equal to \u0027Tu servicio ha sido programado\u0027","duration":221,"startTime":"2023-08-18T09:13:01.361-05:00[America/Bogota]","screenshots":[{"screenshot":"97adf2b7914dddcb5749b4bdbc8327d8b4e959f6db1fd269b3846b4ea4970831.png","timeStamp":1692367981582}],"result":"SUCCESS","precondition":false,"level":2,"lineNumber":0},{"number":35,"description":"jhon clicks on Finalizar Orden de servicio","duration":1026,"startTime":"2023-08-18T09:13:04.730-05:00[America/Bogota]","screenshots":[{"screenshot":"69c0b8091e4fdfd38d22baddfb9f9b15f9048017deca7b9e93ec41627d98f18a.png","timeStamp":1692367985756}],"result":"SUCCESS","precondition":false,"level":2,"lineNumber":0}]}]},{"number":36,"description":"Entonces verifica que se creo correctamente la orden de servicio","duration":12,"startTime":"2023-08-18T09:13:09.956-05:00[America/Bogota]","screenshots":[{"screenshot":"96456ebb1bf739681a22be618260356f706a0668c31313ad7b958b190ffa0afd.png","timeStamp":1692367989968}],"result":"SUCCESS","precondition":false,"level":0,"lineNumber":0}],"userStory":{"id":"proceso-autogestion---agendamiento-de-servicios","storyName":"Proceso Autogestion - Agendamiento de servicios","path":"src/test/resources/features/Autogestion.feature","type":"feature"},"featureTag":{"name":"Features/Proceso Autogestion - Agendamiento de servicios","type":"feature","displayName":"Features/Proceso Autogestion - Agendamiento de servicios"},"title":"Proceso Autogestion - Agendamiento de servicios","tags":[{"name":"CP001_Creacion_OrdenServicio","type":"tag","displayName":"CP001_Creacion_OrdenServicio"},{"name":"Creacion_OrdenServicio","type":"tag","displayName":"Creacion_OrdenServicio"},{"name":"Proceso Autogestion - Agendamiento de servicios","type":"feature","displayName":"Proceso Autogestion - Agendamiento de servicios"}],"startTime":"2023-08-18T09:11:37.798-05:00[America/Bogota]","duration":92172,"projectKey":"","sessionId":"48ab84aafbb19ed28bcc9f00271eddb4","driver":"edge:jhon","isManualTestingUpToDate":false,"manual":false,"testSource":"Cucumber","actors":[{"name":"jhon","can":["browse the web"]}],"result":"SUCCESS"}